package org.bezsahara.minikotlin.builder.opcodes


// The JVM opcode values (with the MethodVisitor method name used to visit them in comment, and
// where '-' means 'same method name as on the previous line').
// See https://docs.oracle.com/javase/specs/jvms/se9/html/jvms-6.html.
@Suppress("SpellCheckingInspection", "unused")
object AllOpCodes {
    const val NOP: Int = 0 // visitInsn
    const val ACONST_NULL: Int = 1 // -
    const val ICONST_M1: Int = 2 // -
    const val ICONST_0: Int = 3 // -
    const val ICONST_1: Int = 4 // -
    const val ICONST_2: Int = 5 // -
    const val ICONST_3: Int = 6 // -
    const val ICONST_4: Int = 7 // -
    const val ICONST_5: Int = 8 // -
    const val LCONST_0: Int = 9 // -
    const val LCONST_1: Int = 10 // -
    const val FCONST_0: Int = 11 // -
    const val FCONST_1: Int = 12 // -
    const val FCONST_2: Int = 13 // -
    const val DCONST_0: Int = 14 // -
    const val DCONST_1: Int = 15 // -
    const val BIPUSH: Int = 16 // visitIntInsn
    const val SIPUSH: Int = 17 // -
    const val LDC: Int = 18 // visitLdcInsn
    const val ILOAD: Int = 21 // visitVarInsn
    const val LLOAD: Int = 22 // -
    const val FLOAD: Int = 23 // -
    const val DLOAD: Int = 24 // -
    const val ALOAD: Int = 25 // -
    const val IALOAD: Int = 46 // visitInsn
    const val LALOAD: Int = 47 // -
    const val FALOAD: Int = 48 // -
    const val DALOAD: Int = 49 // -
    const val AALOAD: Int = 50 // -
    const val BALOAD: Int = 51 // -
    const val CALOAD: Int = 52 // -
    const val SALOAD: Int = 53 // -
    const val ISTORE: Int = 54 // visitVarInsn
    const val LSTORE: Int = 55 // -
    const val FSTORE: Int = 56 // -
    const val DSTORE: Int = 57 // -
    const val ASTORE: Int = 58 // -
    const val IASTORE: Int = 79 // visitInsn
    const val LASTORE: Int = 80 // -
    const val FASTORE: Int = 81 // -
    const val DASTORE: Int = 82 // -
    const val AASTORE: Int = 83 // -
    const val BASTORE: Int = 84 // -
    const val CASTORE: Int = 85 // -
    const val SASTORE: Int = 86 // -
    const val POP: Int = 87 // -
    const val POP2: Int = 88 // -
    const val DUP: Int = 89 // -
    const val DUP_X1: Int = 90 // -
    const val DUP_X2: Int = 91 // -
    const val DUP2: Int = 92 // -
    const val DUP2_X1: Int = 93 // -
    const val DUP2_X2: Int = 94 // -
    const val SWAP: Int = 95 // -
    const val IADD: Int = 96 // -
    const val LADD: Int = 97 // -
    const val FADD: Int = 98 // -
    const val DADD: Int = 99 // -
    const val ISUB: Int = 100 // -
    const val LSUB: Int = 101 // -
    const val FSUB: Int = 102 // -
    const val DSUB: Int = 103 // -
    const val IMUL: Int = 104 // -
    const val LMUL: Int = 105 // -
    const val FMUL: Int = 106 // -
    const val DMUL: Int = 107 // -
    const val IDIV: Int = 108 // -
    const val LDIV: Int = 109 // -
    const val FDIV: Int = 110 // -
    const val DDIV: Int = 111 // -
    const val IREM: Int = 112 // -
    const val LREM: Int = 113 // -
    const val FREM: Int = 114 // -
    const val DREM: Int = 115 // -
    const val INEG: Int = 116 // -
    const val LNEG: Int = 117 // -
    const val FNEG: Int = 118 // -
    const val DNEG: Int = 119 // -
    const val ISHL: Int = 120 // -
    const val LSHL: Int = 121 // -
    const val ISHR: Int = 122 // -
    const val LSHR: Int = 123 // -
    const val IUSHR: Int = 124 // -
    const val LUSHR: Int = 125 // -
    const val IAND: Int = 126 // -
    const val LAND: Int = 127 // -
    const val IOR: Int = 128 // -
    const val LOR: Int = 129 // -
    const val IXOR: Int = 130 // -
    const val LXOR: Int = 131 // -
    const val IINC: Int = 132 // visitIincInsn
    const val I2L: Int = 133 // visitInsn
    const val I2F: Int = 134 // -
    const val I2D: Int = 135 // -
    const val L2I: Int = 136 // -
    const val L2F: Int = 137 // -
    const val L2D: Int = 138 // -
    const val F2I: Int = 139 // -
    const val F2L: Int = 140 // -
    const val F2D: Int = 141 // -
    const val D2I: Int = 142 // -
    const val D2L: Int = 143 // -
    const val D2F: Int = 144 // -
    const val I2B: Int = 145 // -
    const val I2C: Int = 146 // -
    const val I2S: Int = 147 // -
    const val LCMP: Int = 148 // -
    const val FCMPL: Int = 149 // -
    const val FCMPG: Int = 150 // -
    const val DCMPL: Int = 151 // -
    const val DCMPG: Int = 152 // -
    const val IFEQ: Int = 153 // visitJumpInsn
    const val IFNE: Int = 154 // -
    const val IFLT: Int = 155 // -
    const val IFGE: Int = 156 // -
    const val IFGT: Int = 157 // -
    const val IFLE: Int = 158 // -
    const val IF_ICMPEQ: Int = 159 // -
    const val IF_ICMPNE: Int = 160 // -
    const val IF_ICMPLT: Int = 161 // -
    const val IF_ICMPGE: Int = 162 // -
    const val IF_ICMPGT: Int = 163 // -
    const val IF_ICMPLE: Int = 164 // -
    const val IF_ACMPEQ: Int = 165 // -
    const val IF_ACMPNE: Int = 166 // -
    const val GOTO: Int = 167 // -
    const val JSR: Int = 168 // -
    const val RET: Int = 169 // visitVarInsn
    const val TABLESWITCH: Int = 170 // visiTableSwitchInsn
    const val LOOKUPSWITCH: Int = 171 // visitLookupSwitch
    const val IRETURN: Int = 172 // visitInsn
    const val LRETURN: Int = 173 // -
    const val FRETURN: Int = 174 // -
    const val DRETURN: Int = 175 // -
    const val ARETURN: Int = 176 // -
    const val RETURN: Int = 177 // -
    const val GETSTATIC: Int = 178 // visitFieldInsn
    const val PUTSTATIC: Int = 179 // -
    const val GETFIELD: Int = 180 // -
    const val PUTFIELD: Int = 181 // -
    const val INVOKEVIRTUAL: Int = 182 // visitMethodInsn
    const val INVOKESPECIAL: Int = 183 // -
    const val INVOKESTATIC: Int = 184 // -
    const val INVOKEINTERFACE: Int = 185 // -
    const val INVOKEDYNAMIC: Int = 186 // visitInvokeDynamicInsn
    const val NEW: Int = 187 // visitTypeInsn
    const val NEWARRAY: Int = 188 // visitIntInsn
    const val ANEWARRAY: Int = 189 // visitTypeInsn
    const val ARRAYLENGTH: Int = 190 // visitInsn
    const val ATHROW: Int = 191 // -
    const val CHECKCAST: Int = 192 // visitTypeInsn
    const val INSTANCEOF: Int = 193 // -
    const val MONITORENTER: Int = 194 // visitInsn
    const val MONITOREXIT: Int = 195 // -
    const val MULTIANEWARRAY: Int = 197 // visitMultiANewArrayInsn
    const val IFNULL: Int = 198 // visitJumpInsn
    const val IFNONNULL: Int = 199 // -
}
